[
  {
    "Job": "Sr Enterprise Account Executive - California State Government",
    "Location": "Sacramento",
    "Experience": "10+ years",
    "Job Description": "https://careers.servicenow.com/jobs/744000100813795/sr-enterprise-account-executive-california-state-government/",
    "ServiceNow Page": 1
  },
  {
    "Job": "Enterprise Account Executive",
    "Location": "Tokyo",
    "Experience": "7+ years",
    "Job Description": "https://careers.servicenow.com/jobs/744000100797595/enterprise-account-executive/",
    "ServiceNow Page": 1
  },
  {
    "Job": "Staff Systems Engineer",
    "Location": "Dublin",
    "Experience": "8+ years, 6+ years, 3+ years",
    "Job Description": "https://careers.servicenow.com/jobs/744000100766745/staff-systems-engineer/",
    "ServiceNow Page": 1
  },
  {
    "Job": "Sr. Solution Sales Executive - Risk/Security (Healthcare)",
    "Location": "Denver",
    "Experience": "7+ years",
    "Job Description": "https://careers.servicenow.com/jobs/744000100670085/sr-solution-sales-executive-risksecurity-healthcare/",
    "ServiceNow Page": 1
  },
  {
    "Job": "Sr Enterprise Account Executive",
    "Location": "Santa Clara",
    "Experience": "10+ years",
    "Job Description": "https://careers.servicenow.com/jobs/744000100669275/sr-enterprise-account-executive/",
    "ServiceNow Page": 1
  },
  {
    "Job": "Associate Enterprise Account Executive - BFSI",
    "Location": "Mumbai",
    "Experience": "5+ years",
    "Job Description": "https://careers.servicenow.com/jobs/744000100643545/associate-enterprise-account-executive-bfsi/",
    "ServiceNow Page": 1
  },
  {
    "Job": "Enterprise Account Executive",
    "Location": "Tokyo",
    "Experience": "7+ years",
    "Job Description": "https://careers.servicenow.com/jobs/744000100636016/enterprise-account-executive/",
    "ServiceNow Page": 1
  },
  {
    "Job": "Associate Enterprise Account Executive",
    "Location": "Tokyo",
    "Experience": "5+ years",
    "Job Description": "https://careers.servicenow.com/jobs/744000100633405/associate-enterprise-account-executive/",
    "ServiceNow Page": 1
  },
  {
    "Job": "Enterprise Account Executive",
    "Location": "Tokyo",
    "Experience": "7+ years",
    "Job Description": "https://careers.servicenow.com/jobs/744000100631395/enterprise-account-executive/",
    "ServiceNow Page": 1
  },
  {
    "Job": "Solution Sales Executive - CRM & Industry Workflows",
    "Location": "Tokyo",
    "Experience": "5+ years",
    "Job Description": "https://careers.servicenow.com/jobs/744000100629015/solution-sales-executive-crm-industry-workflows/",
    "ServiceNow Page": 1
  },
  {
    "Job": "Associate Enterprise Account Executive",
    "Location": "Tokyo",
    "Experience": "5+ years",
    "Job Description": "https://careers.servicenow.com/jobs/744000100525765/associate-enterprise-account-executive/",
    "ServiceNow Page": 1
  },
  {
    "Job": "Senior Solution Sales Executive",
    "Location": "San Diego",
    "Experience": "7+ years",
    "Job Description": "https://careers.servicenow.com/jobs/744000100411755/senior-solution-sales-executive/",
    "ServiceNow Page": 1
  },
  {
    "Job": "Staff Software Engineer",
    "Location": "Santa Clara",
    "Experience": "6+ years",
    "Job Description": "https://careers.servicenow.com/jobs/744000100407745/staff-software-engineer/",
    "ServiceNow Page": 1
  },
  {
    "Job": "Advisory Solution Consultant - ITOM",
    "Location": "Austin",
    "Experience": "not mentioned",
    "Job Description": "https://careers.servicenow.com/jobs/744000100396575/advisory-solution-consultant-itom/",
    "ServiceNow Page": 1
  },
  {
    "Job": "Senior Software Engineer (Java, Javascript Full Stack)",
    "Location": "Hyderabad",
    "Experience": "7 years",
    "Job Description": "https://careers.servicenow.com/jobs/744000100378547/senior-software-engineer-java-javascript-full-stack/",
    "ServiceNow Page": 1
  },
  {
    "Job": "Senior ServiceNow Developer",
    "Location": "Hyderabad",
    "Experience": "5+ years",
    "Job Description": "https://careers.servicenow.com/jobs/744000100377392/senior-servicenow-developer/",
    "ServiceNow Page": 1
  },
  {
    "Job": "Staff Software Engineer",
    "Location": "Petah Tikva",
    "Experience": "5+ years, 6+ years",
    "Job Description": "https://careers.servicenow.com/jobs/744000100366991/staff-software-engineer/",
    "ServiceNow Page": 1
  },
  {
    "Job": "Senior technical solution consultant",
    "Location": "Hyderabad",
    "Experience": "5+ years",
    "Job Description": "https://careers.servicenow.com/jobs/744000100359745/senior-technical-solution-consultant/",
    "ServiceNow Page": 1
  },
  {
    "Job": "Senior Software Engineer",
    "Location": "Hyderabad",
    "Experience": "8\u00a0years",
    "Job Description": "https://careers.servicenow.com/jobs/744000100348835/senior-software-engineer/",
    "ServiceNow Page": 1
  },
  {
    "Job": "Associate Enterprise Account Executive - TMT",
    "Location": "Mumbai",
    "Experience": "5+ years",
    "Job Description": "https://careers.servicenow.com/jobs/744000100346401/associate-enterprise-account-executive-tmt/",
    "ServiceNow Page": 1
  },
  {
    "Job": "Staff Product Designer",
    "Location": "Bangalore",
    "Experience": "7+ years",
    "Job Description": "https://careers.servicenow.com/jobs/744000100341905/staff-product-designer/",
    "ServiceNow Page": 2
  },
  {
    "Job": "Strategic Customers - Global 360 Deals (Elevate), Senior Director",
    "Location": "Santa Clara",
    "Experience": "10+ years",
    "Job Description": "https://careers.servicenow.com/jobs/744000100322464/strategic-customers-global-360-deals-elevate-senior-director/",
    "ServiceNow Page": 2
  },
  {
    "Job": "Sr Enterprise Account Executive - TMT - Bay Area",
    "Location": "Santa Clara",
    "Experience": "10+ years",
    "Job Description": "https://careers.servicenow.com/jobs/744000100322155/sr-enterprise-account-executive-tmt-bay-area/",
    "ServiceNow Page": 2
  },
  {
    "Job": "Sr. Director, APAC Resell Execution",
    "Location": "Singapore",
    "Experience": "10+ years",
    "Job Description": "https://careers.servicenow.com/jobs/744000100320585/sr-director-apac-resell-execution/",
    "ServiceNow Page": 2
  },
  {
    "Job": "Sr. Solution Consultant, ITAM",
    "Location": "Washington, D.C.",
    "Experience": "7+ years",
    "Job Description": "https://careers.servicenow.com/jobs/744000100310410/sr-solution-consultant-itam/",
    "ServiceNow Page": 2
  },
  {
    "Job": "GTM CIO Autonomous IT Leader",
    "Location": "Santa Clara",
    "Experience": "10+ years, at least 5 years",
    "Job Description": "https://careers.servicenow.com/jobs/744000100310015/gtm-cio-autonomous-it-leader/",
    "ServiceNow Page": 2
  },
  {
    "Job": "Advisory Solution Consultant",
    "Location": "Atlanta",
    "Experience": "7+ years",
    "Job Description": "https://careers.servicenow.com/jobs/744000100308585/advisory-solution-consultant/",
    "ServiceNow Page": 2
  },
  {
    "Job": "Client Director - Healthcare (Strategic Payer) - MA",
    "Location": "Boston",
    "Experience": "2+ years, 7+ years",
    "Job Description": "https://careers.servicenow.com/jobs/744000100306059/client-director-healthcare-strategic-payer-ma/",
    "ServiceNow Page": 2
  },
  {
    "Job": "Client Director - Healthcare (Strategic Payer) - TX",
    "Location": "Addison",
    "Experience": "2+ years, 7+ years",
    "Job Description": "https://careers.servicenow.com/jobs/744000100305873/client-director-healthcare-strategic-payer-tx/",
    "ServiceNow Page": 2
  },
  {
    "Job": "Client Director - Healthcare (Strategic Payer) - KY",
    "Location": "Bowling Green",
    "Experience": "2+ years, 7+ years",
    "Job Description": "https://careers.servicenow.com/jobs/744000100307146/client-director-healthcare-strategic-payer-ky/",
    "ServiceNow Page": 2
  },
  {
    "Job": "Principal Customer Success Executive",
    "Location": "New York",
    "Experience": "12\u00a0years",
    "Job Description": "https://careers.servicenow.com/jobs/744000100306924/principal-customer-success-executive/",
    "ServiceNow Page": 2
  },
  {
    "Job": "Principal Platform Architect- Insurance",
    "Location": "Denver",
    "Experience": "10+ years, 3+ years",
    "Job Description": "https://careers.servicenow.com/jobs/744000100305376/principal-platform-architect-insurance/",
    "ServiceNow Page": 2
  },
  {
    "Job": "Principal Platform Architect- Insurance",
    "Location": "Orlando",
    "Experience": "10+ years, 3+ years",
    "Job Description": "https://careers.servicenow.com/jobs/744000100305549/principal-platform-architect-insurance/",
    "ServiceNow Page": 2
  },
  {
    "Job": "Sr. Technical Consultant, CRM and Industry Workflows - Field Service Mangement",
    "Location": "Addison",
    "Experience": "At least 4 years",
    "Job Description": "https://careers.servicenow.com/jobs/744000100305690/sr-technical-consultant-crm-and-industry-workflows-field-service-mangement/",
    "ServiceNow Page": 2
  },
  {
    "Job": "Principal Platform Architect- Insurance",
    "Location": "Addison",
    "Experience": "10+ years, 3+ years",
    "Job Description": "https://careers.servicenow.com/jobs/744000100305836/principal-platform-architect-insurance/",
    "ServiceNow Page": 2
  },
  {
    "Job": "Principal Platform Architect Banking",
    "Location": "Denver",
    "Experience": "10+ years, 3+ years",
    "Job Description": "https://careers.servicenow.com/jobs/744000100305405/principal-platform-architect-banking/",
    "ServiceNow Page": 2
  },
  {
    "Job": "Principal Platform Architect Banking",
    "Location": "Atlanta",
    "Experience": "10+ years, 3+ years",
    "Job Description": "https://careers.servicenow.com/jobs/744000100305255/principal-platform-architect-banking/",
    "ServiceNow Page": 2
  },
  {
    "Job": "Sr. Advisory Solution Consultant, ITAM",
    "Location": "Boston",
    "Experience": "10+ years",
    "Job Description": "https://careers.servicenow.com/jobs/744000100299595/sr-advisory-solution-consultant-itam/",
    "ServiceNow Page": 2
  },
  {
    "Job": "Mid-Market Protect Account Executive - German Speaker",
    "Location": "Dublin",
    "Experience": "3+ years",
    "Job Description": "https://careers.servicenow.com/jobs/744000100298614/mid-market-protect-account-executive-german-speaker/",
    "ServiceNow Page": 2
  },
  {
    "Job": "Mid-Market Protect Account Executive - French Speaker",
    "Location": "Dublin",
    "Experience": "3 years",
    "Job Description": "https://careers.servicenow.com/jobs/744000100298416/mid-market-protect-account-executive-french-speaker/",
    "ServiceNow Page": 2
  }
]